odoo/addons/shopinvader_customer_autobind/README.rst
odoo/addons/shopinvader_customer_autobind/__init__.py
odoo/addons/shopinvader_customer_autobind/__manifest__.py
odoo/addons/shopinvader_customer_autobind/components/__init__.py
odoo/addons/shopinvader_customer_autobind/components/res_partner_listener.py
odoo/addons/shopinvader_customer_autobind/demo/mail_template.xml
odoo/addons/shopinvader_customer_autobind/i18n/shopinvader_customer_autobind.pot
odoo/addons/shopinvader_customer_autobind/models/__init__.py
odoo/addons/shopinvader_customer_autobind/models/shopinvader_backend.py
odoo/addons/shopinvader_customer_autobind/readme/CONTRIBUTORS.rst
odoo/addons/shopinvader_customer_autobind/readme/DESCRIPTION.rst
odoo/addons/shopinvader_customer_autobind/readme/USAGE.rst
odoo/addons/shopinvader_customer_autobind/static/description/icon.png
odoo/addons/shopinvader_customer_autobind/static/description/index.html
odoo/addons/shopinvader_customer_autobind/tests/__init__.py
odoo/addons/shopinvader_customer_autobind/tests/test_partner_autobind.py
odoo/addons/shopinvader_customer_autobind/views/shopinvader_backend.xml
odoo14_addon_shopinvader_customer_autobind-14.0.1.0.1.dist-info/METADATA
odoo14_addon_shopinvader_customer_autobind-14.0.1.0.1.dist-info/WHEEL
odoo14_addon_shopinvader_customer_autobind-14.0.1.0.1.dist-info/top_level.txt
odoo14_addon_shopinvader_customer_autobind-14.0.1.0.1.dist-info/RECORD
